dulwich_tree.py
dulwich_tree-0.2.dist-info/WHEEL
dulwich_tree-0.2.dist-info/METADATA
dulwich_tree-0.2.dist-info/RECORD
