Metadata-Version: 2.1
Name: dulwich-tree
Version: 0.2
Summary: Library to help make and commit modifications to a tree with Dulwich.
Author-email: Gary van der Merwe <garyvdm@gmail.com>
Requires-Python: >=3.7
Classifier: License :: OSI Approved :: Apache Software License
Classifier: Programming Language :: Python :: Implementation :: CPython
Classifier: Programming Language :: Python :: Implementation :: PyPy
Classifier: Topic :: Software Development :: Version Control
Requires-Dist: dulwich
Project-URL: Source, https://github.com/garyvdm/dulwich-tree
